README.md
setup.py
topsis.py
Topsis_ArpitSingh_102303798.egg-info/PKG-INFO
Topsis_ArpitSingh_102303798.egg-info/SOURCES.txt
Topsis_ArpitSingh_102303798.egg-info/dependency_links.txt
Topsis_ArpitSingh_102303798.egg-info/entry_points.txt
Topsis_ArpitSingh_102303798.egg-info/requires.txt
Topsis_ArpitSingh_102303798.egg-info/top_level.txt
topsis_arpitsingh_102303798.egg-info/PKG-INFO
topsis_arpitsingh_102303798.egg-info/SOURCES.txt
topsis_arpitsingh_102303798.egg-info/dependency_links.txt
topsis_arpitsingh_102303798.egg-info/entry_points.txt
topsis_arpitsingh_102303798.egg-info/requires.txt
topsis_arpitsingh_102303798.egg-info/top_level.txt