Metadata-Version: 2.1
Name: topsis-arpitsingh-102303798
Version: 1.0.0
Summary: A Python package for TOPSIS multi-criteria decision making
Author: Arpit Singh
Author-email: arpit@example.com
Classifier: Programming Language :: Python :: 3
Classifier: License :: OSI Approved :: MIT License
Classifier: Operating System :: OS Independent
